{
"name": "Ese Monday",
  "type": "personal",
  "bio": "Frontend Developer | Technical Wrter | Open Source | DevRel ",
    
  "tags": [
    "Open Source",
    "Javascript",
    "Typescript",
    "NextJS",
    "DevRel"
  ],
   "socials": [
    { "icon": "FaTwitter", "url": "https://twitter.com/esemonday1" },
    { "icon": "FaGithub", "url": "https://github.com/ESE-MONDAY" },
    { "icon": "FaLinkedin", "url": "https://www.linkedin.com/in/ese-monday/" }
  ],
  "links": [
    {
     "name": "Twitter: Follow me",
      "url": "https://twitter.com/esemonday1",
      "icon": "FaTwitter",
      "color": "#00ACEE"  
    },
    {
      "name": "LinkedIn: Follow me",
      "url": "https://www.linkedin.com/in/ese-monday",
      "icon": "FaLinkedin",
      "color": "#00ACEE"
    }
   
  ]
}
